MANIFEST.in
README.md
amazon2csv.py
requirements.txt
setup.cfg
setup.py
amazonscraper/__init__.py
amazonscraper/client.py
amazonscraper.egg-info/PKG-INFO
amazonscraper.egg-info/SOURCES.txt
amazonscraper.egg-info/dependency_links.txt
amazonscraper.egg-info/requires.txt
amazonscraper.egg-info/top_level.txt
test/test_amazonscraper.py