Metadata-Version: 1.2
Name: amazonscraper
Version: 0.1.0
Summary: Package to search for products on Amazon and extract some useful information (title, ratings, number of reviews)
Home-page: https://github.com/tducret/amazon-scraper-python
Author: Thibault Ducret
Author-email: thibault.ducret@gmail.com
License: MIT
Download-URL: https://github.com/tducret/amazon-scraper-python/tarball/0.1.0
Keywords: api,amazon,python,amazonscraper,parsing,python-wrapper,scraping,scraper,parser
Platform: Posix; MacOS X
Classifier: Programming Language :: Python :: 3
Requires-Python: >=3
